django_nose/__init__.py
django_nose/fixture_tables.py
django_nose/plugin.py
django_nose/runner.py
django_nose/testcases.py
django_nose/tools.py
django_nose/utils.py
django_nose/management/__init__.py
django_nose/management/commands/__init__.py
django_nose/management/commands/test.py
django_nose_ng-1.4.3.dist-info/METADATA
django_nose_ng-1.4.3.dist-info/WHEEL
django_nose_ng-1.4.3.dist-info/licenses/AUTHORS.rst
django_nose_ng-1.4.3.dist-info/licenses/LICENSE
django_nose_ng-1.4.3.dist-info/RECORD
