Metadata-Version: 2.4
Name: django-nose-ng
Version: 1.4.3
Summary: Makes your Django tests simple and snappy
Project-URL: Homepage, https://github.com/kkszysiu/django-nose-ng
Project-URL: Documentation, https://django-nose.readthedocs.io
Project-URL: Repository, https://github.com/kkszysiu/django-nose-ng
Project-URL: Changelog, https://github.com/kkszysiu/django-nose-ng/blob/master/changelog.rst
Author-email: Jeff Balogh <me@jeffbalogh.org>
Maintainer-email: Krzysztof Klinikowski <kkszysiu@gmail.com>
License: BSD-3-Clause
License-File: AUTHORS.rst
License-File: LICENSE
Keywords: django,django-nose,nose,testing
Classifier: Development Status :: 5 - Production/Stable
Classifier: Environment :: Web Environment
Classifier: Framework :: Django
Classifier: Framework :: Django :: 4.2
Classifier: Framework :: Django :: 5.0
Classifier: Framework :: Django :: 5.1
Classifier: Intended Audience :: Developers
Classifier: License :: OSI Approved :: BSD License
Classifier: Operating System :: OS Independent
Classifier: Programming Language :: Python
Classifier: Programming Language :: Python :: 3
Classifier: Programming Language :: Python :: 3 :: Only
Classifier: Programming Language :: Python :: 3.11
Classifier: Programming Language :: Python :: 3.12
Classifier: Programming Language :: Python :: 3.13
Classifier: Programming Language :: Python :: 3.14
Classifier: Topic :: Software Development :: Testing
Requires-Python: >=3.11
Requires-Dist: nose-ng>=1.4.3
Provides-Extra: dev
Requires-Dist: build; extra == 'dev'
Requires-Dist: coverage>=7.0; extra == 'dev'
Requires-Dist: django-environ; extra == 'dev'
Requires-Dist: django>=4.2; extra == 'dev'
Requires-Dist: ruff>=0.8.0; extra == 'dev'
Requires-Dist: tox>=4.0; extra == 'dev'
Requires-Dist: twine; extra == 'dev'
Provides-Extra: docs
Requires-Dist: django-environ; extra == 'docs'
Requires-Dist: django>=4.2; extra == 'docs'
Requires-Dist: sphinx>=7.0; extra == 'docs'
Provides-Extra: test
Requires-Dist: coverage>=7.0; extra == 'test'
Requires-Dist: django-environ; extra == 'test'
Requires-Dist: django>=4.2; extra == 'test'
